comfy_sdk/__init__.py
comfy_sdk/_base_client.py
comfy_sdk/_client.py
comfy_sdk/_models.py
comfy_sdk/_version.py
comfy_sdk/api.py
comfy_sdk/client.py
comfy_sdk/resources/__init__.py
comfy_sdk/resources/images.py
comfy_sdk/resources/models.py
comfy_sdk/resources/prompt.py
comfy_sdk/resources/queue.py
comfy_sdk/resources/system.py
comfy_sdk/resources/templates.py
comfy_sdk/resources/user.py
comfyui_python_client-0.1.0.dist-info/METADATA
comfyui_python_client-0.1.0.dist-info/WHEEL
comfyui_python_client-0.1.0.dist-info/top_level.txt
comfyui_python_client-0.1.0.dist-info/RECORD
